pubmed_api/__init__.py
pubmed_api/api.py
pubmed_api/pubmed.py
pubmed_api-2.0.0.dist-info/LICENSE.md
pubmed_api-2.0.0.dist-info/METADATA
pubmed_api-2.0.0.dist-info/WHEEL
pubmed_api-2.0.0.dist-info/top_level.txt
pubmed_api-2.0.0.dist-info/RECORD
