Metadata-Version: 2.1
Name: pubmed-api
Version: 2.0.0
Summary: Runs PubMed search strings over pubmed API using a batch logic
Home-page: https://github.com/shivam221098/pubmed-api-v1
Author: Shivam Singh
Author-email: shivam221098@gmail.com
License-File: LICENSE.md
Requires-Dist: xmltodict
Requires-Dist: requests
